strarting_apache2_from_linode_server/__init__.py
strarting_apache2_from_linode_server/monitor.py
strarting_apache2_from_linode_server-0.1.0.dist-info/entry_points.txt
strarting_apache2_from_linode_server-0.1.0.dist-info/WHEEL
strarting_apache2_from_linode_server-0.1.0.dist-info/METADATA
strarting_apache2_from_linode_server-0.1.0.dist-info/RECORD
